hyphenfrac/__init__.py
hyphenfrac-2.0.dist-info/LICENSE
hyphenfrac-2.0.dist-info/METADATA
hyphenfrac-2.0.dist-info/WHEEL
hyphenfrac-2.0.dist-info/top_level.txt
hyphenfrac-2.0.dist-info/RECORD
