Metadata-Version: 2.1
Name: hyphenfrac
Version: 2.0
Summary: A basic utility designed to prettify and visualize fractions.
Home-page: https://github.com/xyzpw/hyphenfrac/
Author: xyzpw
Maintainer: xyzpw
License: MIT
Classifier: Programming Language :: Python :: 3
Classifier: Programming Language :: Python :: 3.7
Classifier: Programming Language :: Python :: 3.8
Classifier: Programming Language :: Python :: 3.9
Classifier: Programming Language :: Python :: 3.10
Classifier: Programming Language :: Python :: 3.11
Classifier: Operating System :: POSIX :: Linux
Classifier: Intended Audience :: Developers
Classifier: Environment :: Console :: Curses
Classifier: Environment :: Console
Requires-Python: >=3.7
License-File: LICENSE
